yamale/VERSION
yamale/__init__.py
yamale/command_line.py
yamale/util.py
yamale/version.py
yamale/yamale.py
yamale/yamale_error.py
yamale/yamale_testcase.py
yamale/readers/__init__.py
yamale/readers/yaml_reader.py
yamale/readers/tests/__init__.py
yamale/readers/tests/test_bad_file.py
yamale/readers/tests/test_yaml.py
yamale/schema/__init__.py
yamale/schema/datapath.py
yamale/schema/schema.py
yamale/schema/validationresults.py
yamale/syntax/__init__.py
yamale/syntax/parser.py
yamale/syntax/tests/__init__.py
yamale/syntax/tests/test_parser.py
yamale/tests/__init__.py
yamale/tests/test_command_line.py
yamale/tests/test_functional.py
yamale/tests/test_meta_test.py
yamale/tests/fixtures/any.yaml
yamale/tests/fixtures/any_bad.yaml
yamale/tests/fixtures/any_good.yaml
yamale/tests/fixtures/any_undefined.yaml
yamale/tests/fixtures/any_undefined_schema.yaml
yamale/tests/fixtures/bad_schema.yaml
yamale/tests/fixtures/bad_schema_rce.yaml
yamale/tests/fixtures/bad_schema_rce2.yaml
yamale/tests/fixtures/bad_schema_rce3.yaml
yamale/tests/fixtures/bad_schema_rce4.yaml
yamale/tests/fixtures/custom_types.yaml
yamale/tests/fixtures/custom_types_bad.yaml
yamale/tests/fixtures/custom_types_good.yaml
yamale/tests/fixtures/empty_schema.yaml
yamale/tests/fixtures/include_validator.yaml
yamale/tests/fixtures/include_validator_bad.yaml
yamale/tests/fixtures/include_validator_good.yaml
yamale/tests/fixtures/ip.yaml
yamale/tests/fixtures/ip_bad.yaml
yamale/tests/fixtures/ip_good.yaml
yamale/tests/fixtures/issue_22.yaml
yamale/tests/fixtures/issue_22_good.yaml
yamale/tests/fixtures/issue_50.yaml
yamale/tests/fixtures/issue_50_good.yaml
yamale/tests/fixtures/keywords.yaml
yamale/tests/fixtures/keywords_bad.yaml
yamale/tests/fixtures/keywords_good.yaml
yamale/tests/fixtures/list_include.yaml
yamale/tests/fixtures/list_include_good.yaml
yamale/tests/fixtures/lists.yaml
yamale/tests/fixtures/lists_bad.yaml
yamale/tests/fixtures/lists_bad2.yaml
yamale/tests/fixtures/lists_good.yaml
yamale-5.3.0.dist-info/LICENSE
yamale-5.3.0.dist-info/METADATA
yamale-5.3.0.dist-info/WHEEL
yamale-5.3.0.dist-info/entry_points.txt
yamale-5.3.0.dist-info/top_level.txt
yamale-5.3.0.dist-info/RECORD
